binary2bcd_double_dabble.v
module top_modeule (
    input wire [7:0]in_binary,
    output wire [7:0]packed_bcd,
    output wire [15:0]unpacked_bcd,
    input wire clk,
    input wire rst_n
);
    reg [15:0]scratch_pad;
    always @( *) begin
        scratch_pad = {8'b0000_0000, in_binary};
        for (integer i = 1; i < 8 ; i = i + 1) begin
            scratch_pad= scratch_pad << 1;
            if (scratch_pad[11:8] > 4'b0100) begin
                scratch_pad[11:8] = scratch_pad[11:8] + 4'b0011;
            end 
        end
        scratch_pad = scratch_pad << 1;
    end
    assign packed_bcd = scratch_pad[15:8];
    assign unpacked_bcd = {4'b0000, scratch_pad[15:12], 4'b0000, scratch_pad[11:8]};
endmodule

binary2bcd_double_dabble-tb.v
`include "binary2bcd_double_dabble.v"
//~ `New testbench
`timescale  1ns / 1ps

module tb_top_modeule;

// top_modeule Parameters
parameter PERIOD  = 10;
parameter LARGE_NUMBER = 255;
integer i, j, error;


// top_modeule Inputs
reg [7:0] in_binary = 0;
reg clk;
reg rst_n;

// top_modeule Outputs
wire [7:0] packed_bcd;
wire [15:0] unpacked_bcd;

// there you can read data from the solution file,and store in the register.
reg [7:0] solution [0:99];
initial begin
  $readmemb("solution.dat",solution);
end


top_modeule  u_top_modeule (
    .in_binary(in_binary[7:0]),
    .clk(clk),
    .rst_n(rst_n),
    .packed_bcd(packed_bcd[7:0]),
    .unpacked_bcd(unpacked_bcd[15:0])
);


//generate clk
always #(PERIOD/2) clk = ~clk;

initial begin
    clk = 1;
    rst_n = 1;

    #(PERIOD) rst_n = 0; // system reset
    #(PERIOD) rst_n = 1;

end

//dump the waveform of the simulation
initial begin
    $dumpfile("binary2bcd_double_dabble-tb.vcd");
    $dumpvars;
end

// testing input 
initial
begin
    wait(rst_n == 0);
    wait(rst_n == 1);
    in_binary = 8'b0000_0000;
    for (i = 0; i < LARGE_NUMBER; i = i + 1) begin
        @ (negedge clk) in_binary = in_binary + 1;
    end
end

//check result
initial begin
    error = 0; // error count
    wait(rst_n == 0);
    wait(rst_n == 1);
    //auto check
    for (j = 0; j <= 99; j = j + 1) begin //compare the solution with the simulation result.
        @(negedge clk);
        if (packed_bcd != solution[j][7:0]) begin
            error = error + 1;
            $display("pattern number No.%d is wrong at %t", j, $time);
            $display("your answer is %b, but the correct answer is %b", packed_bcd, solution[j]);
        end
    end

    if (error == 0) begin
        $display("Your answer is correct!");
    end else begin
        $display("Your answer is wrong!");
    end

    #(PERIOD)$finish;

end

endmodule

binary2bcd_double_dabble-tb.vcd
$date
	Wed Jan 08 17:45:54 2025
$end
$version
	Icarus Verilog
$end
$timescale
	1ps
$end
$scope module tb_top_modeule $end
$var wire 16 ! unpacked_bcd [15:0] $end
$var wire 8 " packed_bcd [7:0] $end
$var reg 1 # clk $end
$var reg 8 $ in_binary [7:0] $end
$var reg 1 % rst_n $end
$var integer 32 & error [31:0] $end
$var integer 32 ' i [31:0] $end
$var integer 32 ( j [31:0] $end
$scope module u_top_modeule $end
$var wire 1 # clk $end
$var wire 8 ) in_binary [7:0] $end
$var wire 1 % rst_n $end
$var wire 16 * unpacked_bcd [15:0] $end
$var wire 8 + packed_bcd [7:0] $end
$var reg 16 , scratch_pad [15:0] $end
$scope begin $ivl_for_loop0 $end
$var integer 32 - i [31:0] $end
$upscope $end
$upscope $end
$upscope $end
$enddefinitions $end
#0
$dumpvars
b1000 -
b0 ,
b0 +
b0 *
b0 )
bx (
bx '
b0 &
1%
b0 $
1#
b0 "
b0 !
$end
#5000
0#
#10000
1#
0%
#15000
0#
#20000
b0 (
b0 '
1#
1%
#25000
b1 "
b1 +
b1 !
b1 *
b1000 -
b100000000 ,
b1 '
b1 $
b1 )
b1 (
0#
#30000
1#
#35000
b10 "
b10 +
b10 !
b10 *
b1000 -
b1000000000 ,
b10 (
b10 '
b10 $
b10 )
0#
#40000
1#
#45000
b11 "
b11 +
b11 !
b11 *
b1000 -
b1100000000 ,
b11 '
b11 $
b11 )
b11 (
0#
#50000
1#
#55000
b100 "
b100 +
b100 !
b100 *
b1000 -
b10000000000 ,
b100 (
b100 '
b100 $
b100 )
0#
#60000
1#
#65000
b101 "
b101 +
b101 !
b101 *
b1000 -
b10100000000 ,
b101 '
b101 $
b101 )
b101 (
0#
#70000
1#
#75000
b110 "
b110 +
b110 !
b110 *
b1000 -
b11000000000 ,
b110 (
b110 '
b110 $
b110 )
0#
#80000
1#
#85000
b111 "
b111 +
b111 !
b111 *
b1000 -
b11100000000 ,
b111 '
b111 $
b111 )
b111 (
0#
#90000
1#
#95000
b1000 "
b1000 +
b1000 !
b1000 *
b1000 -
b100000000000 ,
b1000 (
b1000 '
b1000 $
b1000 )
0#
#100000
1#
#105000
b1001 "
b1001 +
b1001 !
b1001 *
b1000 -
b100100000000 ,
b1001 '
b1001 $
b1001 )
b1001 (
0#
#110000
1#
#115000
b10000 "
b10000 +
b100000000 !
b100000000 *
b1000 -
b1000000000000 ,
b1010 (
b1010 '
b1010 $
b1010 )
0#
#120000
1#
#125000
b100000001 !
b100000001 *
b10001 "
b10001 +
b1000 -
b1000100000000 ,
b1011 '
b1011 $
b1011 )
b1011 (
0#
#130000
1#
#135000
b10010 "
b10010 +
b100000010 !
b100000010 *
b1000 -
b1001000000000 ,
b1100 (
b1100 '
b1100 $
b1100 )
0#
#140000
1#
#145000
b10011 "
b10011 +
b100000011 !
b100000011 *
b1000 -
b1001100000000 ,
b1101 '
b1101 $
b1101 )
b1101 (
0#
#150000
1#
#155000
b10100 "
b10100 +
b100000100 !
b100000100 *
b1000 -
b1010000000000 ,
b1110 (
b1110 '
b1110 $
b1110 )
0#
#160000
1#
#165000
b10101 "
b10101 +
b100000101 !
b100000101 *
b1000 -
b1010100000000 ,
b1111 '
b1111 $
b1111 )
b1111 (
0#
#170000
1#
#175000
b10110 "
b10110 +
b100000110 !
b100000110 *
b1000 -
b1011000000000 ,
b10000 (
b10000 '
b10000 $
b10000 )
0#
#180000
1#
#185000
b10111 "
b10111 +
b100000111 !
b100000111 *
b1000 -
b1011100000000 ,
b10001 '
b10001 $
b10001 )
b10001 (
0#
#190000
1#
#195000
b11000 "
b11000 +
b100001000 !
b100001000 *
b1000 -
b1100000000000 ,
b10010 (
b10010 '
b10010 $
b10010 )
0#
#200000
1#
#205000
b11001 "
b11001 +
b100001001 !
b100001001 *
b1000 -
b1100100000000 ,
b10011 '
b10011 $
b10011 )
b10011 (
0#
#210000
1#
#215000
b100000 "
b100000 +
b1000000000 !
b1000000000 *
b1000 -
b10000000000000 ,
b10100 (
b10100 '
b10100 $
b10100 )
0#
#220000
1#
#225000
b1000000001 !
b1000000001 *
b100001 "
b100001 +
b1000 -
b10000100000000 ,
b10101 '
b10101 $
b10101 )
b10101 (
0#
#230000
1#
#235000
b100010 "
b100010 +
b1000000010 !
b1000000010 *
b1000 -
b10001000000000 ,
b10110 (
b10110 '
b10110 $
b10110 )
0#
#240000
1#
#245000
b100011 "
b100011 +
b1000000011 !
b1000000011 *
b1000 -
b10001100000000 ,
b10111 '
b10111 $
b10111 )
b10111 (
0#
#250000
1#
#255000
b100100 "
b100100 +
b1000000100 !
b1000000100 *
b1000 -
b10010000000000 ,
b11000 (
b11000 '
b11000 $
b11000 )
0#
#260000
1#
#265000
b100101 "
b100101 +
b1000000101 !
b1000000101 *
b1000 -
b10010100000000 ,
b11001 '
b11001 $
b11001 )
b11001 (
0#
#270000
1#
#275000
b100110 "
b100110 +
b1000000110 !
b1000000110 *
b1000 -
b10011000000000 ,
b11010 (
b11010 '
b11010 $
b11010 )
0#
#280000
1#
#285000
b100111 "
b100111 +
b1000000111 !
b1000000111 *
b1000 -
b10011100000000 ,
b11011 '
b11011 $
b11011 )
b11011 (
0#
#290000
1#
#295000
b101000 "
b101000 +
b1000001000 !
b1000001000 *
b1000 -
b10100000000000 ,
b11100 (
b11100 '
b11100 $
b11100 )
0#
#300000
1#
#305000
b101001 "
b101001 +
b1000001001 !
b1000001001 *
b1000 -
b10100100000000 ,
b11101 '
b11101 $
b11101 )
b11101 (
0#
#310000
1#
#315000
b110000 "
b110000 +
b1100000000 !
b1100000000 *
b1000 -
b11000000000000 ,
b11110 (
b11110 '
b11110 $
b11110 )
0#
#320000
1#
#325000
b1100000001 !
b1100000001 *
b110001 "
b110001 +
b1000 -
b11000100000000 ,
b11111 '
b11111 $
b11111 )
b11111 (
0#
#330000
1#
#335000
b110010 "
b110010 +
b1100000010 !
b1100000010 *
b1000 -
b11001000000000 ,
b100000 (
b100000 '
b100000 $
b100000 )
0#
#340000
1#
#345000
b110011 "
b110011 +
b1100000011 !
b1100000011 *
b1000 -
b11001100000000 ,
b100001 '
b100001 $
b100001 )
b100001 (
0#
#350000
1#
#355000
b110100 "
b110100 +
b1100000100 !
b1100000100 *
b1000 -
b11010000000000 ,
b100010 (
b100010 '
b100010 $
b100010 )
0#
#360000
1#
#365000
b110101 "
b110101 +
b1100000101 !
b1100000101 *
b1000 -
b11010100000000 ,
b100011 '
b100011 $
b100011 )
b100011 (
0#
#370000
1#
#375000
b110110 "
b110110 +
b1100000110 !
b1100000110 *
b1000 -
b11011000000000 ,
b100100 (
b100100 '
b100100 $
b100100 )
0#
#380000
1#
#385000
b110111 "
b110111 +
b1100000111 !
b1100000111 *
b1000 -
b11011100000000 ,
b100101 '
b100101 $
b100101 )
b100101 (
0#
#390000
1#
#395000
b111000 "
b111000 +
b1100001000 !
b1100001000 *
b1000 -
b11100000000000 ,
b100110 (
b100110 '
b100110 $
b100110 )
0#
#400000
1#
#405000
b111001 "
b111001 +
b1100001001 !
b1100001001 *
b1000 -
b11100100000000 ,
b100111 '
b100111 $
b100111 )
b100111 (
0#
#410000
1#
#415000
b1000000 "
b1000000 +
b10000000000 !
b10000000000 *
b1000 -
b100000000000000 ,
b101000 (
b101000 '
b101000 $
b101000 )
0#
#420000
1#
#425000
b10000000001 !
b10000000001 *
b1000001 "
b1000001 +
b1000 -
b100000100000000 ,
b101001 '
b101001 $
b101001 )
b101001 (
0#
#430000
1#
#435000
b1000010 "
b1000010 +
b10000000010 !
b10000000010 *
b1000 -
b100001000000000 ,
b101010 (
b101010 '
b101010 $
b101010 )
0#
#440000
1#
#445000
b1000011 "
b1000011 +
b10000000011 !
b10000000011 *
b1000 -
b100001100000000 ,
b101011 '
b101011 $
b101011 )
b101011 (
0#
#450000
1#
#455000
b1000100 "
b1000100 +
b10000000100 !
b10000000100 *
b1000 -
b100010000000000 ,
b101100 (
b101100 '
b101100 $
b101100 )
0#
#460000
1#
#465000
b1000101 "
b1000101 +
b10000000101 !
b10000000101 *
b1000 -
b100010100000000 ,
b101101 '
b101101 $
b101101 )
b101101 (
0#
#470000
1#
#475000
b1000110 "
b1000110 +
b10000000110 !
b10000000110 *
b1000 -
b100011000000000 ,
b101110 (
b101110 '
b101110 $
b101110 )
0#
#480000
1#
#485000
b1000111 "
b1000111 +
b10000000111 !
b10000000111 *
b1000 -
b100011100000000 ,
b101111 '
b101111 $
b101111 )
b101111 (
0#
#490000
1#
#495000
b1001000 "
b1001000 +
b10000001000 !
b10000001000 *
b1000 -
b100100000000000 ,
b110000 (
b110000 '
b110000 $
b110000 )
0#
#500000
1#
#505000
b1001001 "
b1001001 +
b10000001001 !
b10000001001 *
b1000 -
b100100100000000 ,
b110001 '
b110001 $
b110001 )
b110001 (
0#
#510000
1#
#515000
b1010000 "
b1010000 +
b10100000000 !
b10100000000 *
b1000 -
b101000000000000 ,
b110010 (
b110010 '
b110010 $
b110010 )
0#
#520000
1#
#525000
b10100000001 !
b10100000001 *
b1010001 "
b1010001 +
b1000 -
b101000100000000 ,
b110011 '
b110011 $
b110011 )
b110011 (
0#
#530000
1#
#535000
b1010010 "
b1010010 +
b10100000010 !
b10100000010 *
b1000 -
b101001000000000 ,
b110100 (
b110100 '
b110100 $
b110100 )
0#
#540000
1#
#545000
b1010011 "
b1010011 +
b10100000011 !
b10100000011 *
b1000 -
b101001100000000 ,
b110101 '
b110101 $
b110101 )
b110101 (
0#
#550000
1#
#555000
b1010100 "
b1010100 +
b10100000100 !
b10100000100 *
b1000 -
b101010000000000 ,
b110110 (
b110110 '
b110110 $
b110110 )
0#
#560000
1#
#565000
b1010101 "
b1010101 +
b10100000101 !
b10100000101 *
b1000 -
b101010100000000 ,
b110111 '
b110111 $
b110111 )
b110111 (
0#
#570000
1#
#575000
b1010110 "
b1010110 +
b10100000110 !
b10100000110 *
b1000 -
b101011000000000 ,
b111000 (
b111000 '
b111000 $
b111000 )
0#
#580000
1#
#585000
b1010111 "
b1010111 +
b10100000111 !
b10100000111 *
b1000 -
b101011100000000 ,
b111001 '
b111001 $
b111001 )
b111001 (
0#
#590000
1#
#595000
b1011000 "
b1011000 +
b10100001000 !
b10100001000 *
b1000 -
b101100000000000 ,
b111010 (
b111010 '
b111010 $
b111010 )
0#
#600000
1#
#605000
b1011001 "
b1011001 +
b10100001001 !
b10100001001 *
b1000 -
b101100100000000 ,
b111011 '
b111011 $
b111011 )
b111011 (
0#
#610000
1#
#615000
b1100000 "
b1100000 +
b11000000000 !
b11000000000 *
b1000 -
b110000000000000 ,
b111100 (
b111100 '
b111100 $
b111100 )
0#
#620000
1#
#625000
b11000000001 !
b11000000001 *
b1100001 "
b1100001 +
b1000 -
b110000100000000 ,
b111101 '
b111101 $
b111101 )
b111101 (
0#
#630000
1#
#635000
b1100010 "
b1100010 +
b11000000010 !
b11000000010 *
b1000 -
b110001000000000 ,
b111110 (
b111110 '
b111110 $
b111110 )
0#
#640000
1#
#645000
b1100011 "
b1100011 +
b11000000011 !
b11000000011 *
b1000 -
b110001100000000 ,
b111111 '
b111111 $
b111111 )
b111111 (
0#
#650000
1#
#655000
b1100100 "
b1100100 +
b11000000100 !
b11000000100 *
b1000 -
b110010000000000 ,
b1000000 (
b1000000 '
b1000000 $
b1000000 )
0#
#660000
1#
#665000
b1100101 "
b1100101 +
b11000000101 !
b11000000101 *
b1000 -
b110010100000000 ,
b1000001 '
b1000001 $
b1000001 )
b1000001 (
0#
#670000
1#
#675000
b1100110 "
b1100110 +
b11000000110 !
b11000000110 *
b1000 -
b110011000000000 ,
b1000010 (
b1000010 '
b1000010 $
b1000010 )
0#
#680000
1#
#685000
b1100111 "
b1100111 +
b11000000111 !
b11000000111 *
b1000 -
b110011100000000 ,
b1000011 '
b1000011 $
b1000011 )
b1000011 (
0#
#690000
1#
#695000
b1101000 "
b1101000 +
b11000001000 !
b11000001000 *
b1000 -
b110100000000000 ,
b1000100 (
b1000100 '
b1000100 $
b1000100 )
0#
#700000
1#
#705000
b1101001 "
b1101001 +
b11000001001 !
b11000001001 *
b1000 -
b110100100000000 ,
b1000101 '
b1000101 $
b1000101 )
b1000101 (
0#
#710000
1#
#715000
b1110000 "
b1110000 +
b11100000000 !
b11100000000 *
b1000 -
b111000000000000 ,
b1000110 (
b1000110 '
b1000110 $
b1000110 )
0#
#720000
1#
#725000
b11100000001 !
b11100000001 *
b1110001 "
b1110001 +
b1000 -
b111000100000000 ,
b1000111 '
b1000111 $
b1000111 )
b1000111 (
0#
#730000
1#
#735000
b1110010 "
b1110010 +
b11100000010 !
b11100000010 *
b1000 -
b111001000000000 ,
b1001000 (
b1001000 '
b1001000 $
b1001000 )
0#
#740000
1#
#745000
b1110011 "
b1110011 +
b11100000011 !
b11100000011 *
b1000 -
b111001100000000 ,
b1001001 '
b1001001 $
b1001001 )
b1001001 (
0#
#750000
1#
#755000
b1110100 "
b1110100 +
b11100000100 !
b11100000100 *
b1000 -
b111010000000000 ,
b1001010 (
b1001010 '
b1001010 $
b1001010 )
0#
#760000
1#
#765000
b1110101 "
b1110101 +
b11100000101 !
b11100000101 *
b1000 -
b111010100000000 ,
b1001011 '
b1001011 $
b1001011 )
b1001011 (
0#
#770000
1#
#775000
b1110110 "
b1110110 +
b11100000110 !
b11100000110 *
b1000 -
b111011000000000 ,
b1001100 (
b1001100 '
b1001100 $
b1001100 )
0#
#780000
1#
#785000
b1110111 "
b1110111 +
b11100000111 !
b11100000111 *
b1000 -
b111011100000000 ,
b1001101 '
b1001101 $
b1001101 )
b1001101 (
0#
#790000
1#
#795000
b1111000 "
b1111000 +
b11100001000 !
b11100001000 *
b1000 -
b111100000000000 ,
b1001110 (
b1001110 '
b1001110 $
b1001110 )
0#
#800000
1#
#805000
b1111001 "
b1111001 +
b11100001001 !
b11100001001 *
b1000 -
b111100100000000 ,
b1001111 '
b1001111 $
b1001111 )
b1001111 (
0#
#810000
1#
#815000
b10000000 "
b10000000 +
b100000000000 !
b100000000000 *
b1000 -
b1000000000000000 ,
b1010000 (
b1010000 '
b1010000 $
b1010000 )
0#
#820000
1#
#825000
b100000000001 !
b100000000001 *
b10000001 "
b10000001 +
b1000 -
b1000000100000000 ,
b1010001 '
b1010001 $
b1010001 )
b1010001 (
0#
#830000
1#
#835000
b10000010 "
b10000010 +
b100000000010 !
b100000000010 *
b1000 -
b1000001000000000 ,
b1010010 (
b1010010 '
b1010010 $
b1010010 )
0#
#840000
1#
#845000
b10000011 "
b10000011 +
b100000000011 !
b100000000011 *
b1000 -
b1000001100000000 ,
b1010011 '
b1010011 $
b1010011 )
b1010011 (
0#
#850000
1#
#855000
b10000100 "
b10000100 +
b100000000100 !
b100000000100 *
b1000 -
b1000010000000000 ,
b1010100 (
b1010100 '
b1010100 $
b1010100 )
0#
#860000
1#
#865000
b10000101 "
b10000101 +
b100000000101 !
b100000000101 *
b1000 -
b1000010100000000 ,
b1010101 '
b1010101 $
b1010101 )
b1010101 (
0#
#870000
1#
#875000
b10000110 "
b10000110 +
b100000000110 !
b100000000110 *
b1000 -
b1000011000000000 ,
b1010110 (
b1010110 '
b1010110 $
b1010110 )
0#
#880000
1#
#885000
b10000111 "
b10000111 +
b100000000111 !
b100000000111 *
b1000 -
b1000011100000000 ,
b1010111 '
b1010111 $
b1010111 )
b1010111 (
0#
#890000
1#
#895000
b10001000 "
b10001000 +
b100000001000 !
b100000001000 *
b1000 -
b1000100000000000 ,
b1011000 (
b1011000 '
b1011000 $
b1011000 )
0#
#900000
1#
#905000
b10001001 "
b10001001 +
b100000001001 !
b100000001001 *
b1000 -
b1000100100000000 ,
b1011001 '
b1011001 $
b1011001 )
b1011001 (
0#
#910000
1#
#915000
b10010000 "
b10010000 +
b100100000000 !
b100100000000 *
b1000 -
b1001000000000000 ,
b1011010 (
b1011010 '
b1011010 $
b1011010 )
0#
#920000
1#
#925000
b100100000001 !
b100100000001 *
b10010001 "
b10010001 +
b1000 -
b1001000100000000 ,
b1011011 '
b1011011 $
b1011011 )
b1011011 (
0#
#930000
1#
#935000
b10010010 "
b10010010 +
b100100000010 !
b100100000010 *
b1000 -
b1001001000000000 ,
b1011100 (
b1011100 '
b1011100 $
b1011100 )
0#
#940000
1#
#945000
b10010011 "
b10010011 +
b100100000011 !
b100100000011 *
b1000 -
b1001001100000000 ,
b1011101 '
b1011101 $
b1011101 )
b1011101 (
0#
#950000
1#
#955000
b10010100 "
b10010100 +
b100100000100 !
b100100000100 *
b1000 -
b1001010000000000 ,
b1011110 (
b1011110 '
b1011110 $
b1011110 )
0#
#960000
1#
#965000
b10010101 "
b10010101 +
b100100000101 !
b100100000101 *
b1000 -
b1001010100000000 ,
b1011111 '
b1011111 $
b1011111 )
b1011111 (
0#
#970000
1#
#975000
b10010110 "
b10010110 +
b100100000110 !
b100100000110 *
b1000 -
b1001011000000000 ,
b1100000 (
b1100000 '
b1100000 $
b1100000 )
0#
#980000
1#
#985000
b10010111 "
b10010111 +
b100100000111 !
b100100000111 *
b1000 -
b1001011100000000 ,
b1100001 '
b1100001 $
b1100001 )
b1100001 (
0#
#990000
1#
#995000
b10011000 "
b10011000 +
b100100001000 !
b100100001000 *
b1000 -
b1001100000000000 ,
b1100010 (
b1100010 '
b1100010 $
b1100010 )
0#
#1000000
1#
#1005000
b10011001 "
b10011001 +
b100100001001 !
b100100001001 *
b1000 -
b1001100100000000 ,
b1100011 '
b1100011 $
b1100011 )
b1100011 (
0#
#1010000
1#
#1015000
b10100000 "
b10100000 +
b101000000000 !
b101000000000 *
b1000 -
b1010000000000000 ,
b1100100 (
b1100100 '
b1100100 $
b1100100 )
0#
#1020000
1#
#1025000
b101000000001 !
b101000000001 *
b10100001 "
b10100001 +
b1000 -
b1010000100000000 ,
b1100101 '
b1100101 $
b1100101 )
0#
